<?xml version="1.0" encoding="UTF-8" ?>
<!DOCTYPE mapper PUBLIC "-//mybatis.org//DTD Mapper 3.0//EN" "http://mybatis.org/dtd/mybatis-3-mapper.dtd" >
<mapper namespace="com.qinjiangbo.gen.dao.SysSetMapper" >
  <resultMap id="BaseResultMap" type="com.qinjiangbo.gen.model.SysSet" >
    <!--
      WARNING - @mbggenerated
      This element is automatically generated by MyBatis Generator, do not modify.
      This element was generated on Tue Jun 21 00:00:04 CST 2016.
    -->
    <id column="skey" property="skey" jdbcType="VARCHAR" />
    <result column="sname" property="sname" jdbcType="VARCHAR" />
    <result column="svalue" property="svalue" jdbcType="VARCHAR" />
    <result column="sort" property="sort" jdbcType="INTEGER" />
    <result column="remark" property="remark" jdbcType="VARCHAR" />
    <result column="time_update" property="timeUpdate" jdbcType="TIMESTAMP" />
    <result column="status" property="status" jdbcType="INTEGER" />
    <result column="user_id" property="userId" jdbcType="BIGINT" />
    <result column="class" property="clazz" jdbcType="VARCHAR" />
  </resultMap>
  <sql id="Example_Where_Clause" >
    <!--
      WARNING - @mbggenerated
      This element is automatically generated by MyBatis Generator, do not modify.
      This element was generated on Tue Jun 21 00:00:04 CST 2016.
    -->
    <where >
      <foreach collection="oredCriteria" item="criteria" separator="or" >
        <if test="criteria.valid" >
          <trim prefix="(" suffix=")" prefixOverrides="and" >
            <foreach collection="criteria.criteria" item="criterion" >
              <choose >
                <when test="criterion.noValue" >
                  and ${criterion.condition}
                </when>
                <when test="criterion.singleValue" >
                  and ${criterion.condition} #{criterion.value}
                </when>
                <when test="criterion.betweenValue" >
                  and ${criterion.condition} #{criterion.value} and #{criterion.secondValue}
                </when>
                <when test="criterion.listValue" >
                  and ${criterion.condition}
                  <foreach collection="criterion.value" item="listItem" open="(" close=")" separator="," >
                    #{listItem}
                  </foreach>
                </when>
              </choose>
            </foreach>
          </trim>
        </if>
      </foreach>
    </where>
  </sql>
  <sql id="Update_By_Example_Where_Clause" >
    <!--
      WARNING - @mbggenerated
      This element is automatically generated by MyBatis Generator, do not modify.
      This element was generated on Tue Jun 21 00:00:04 CST 2016.
    -->
    <where >
      <foreach collection="example.oredCriteria" item="criteria" separator="or" >
        <if test="criteria.valid" >
          <trim prefix="(" suffix=")" prefixOverrides="and" >
            <foreach collection="criteria.criteria" item="criterion" >
              <choose >
                <when test="criterion.noValue" >
                  and ${criterion.condition}
                </when>
                <when test="criterion.singleValue" >
                  and ${criterion.condition} #{criterion.value}
                </when>
                <when test="criterion.betweenValue" >
                  and ${criterion.condition} #{criterion.value} and #{criterion.secondValue}
                </when>
                <when test="criterion.listValue" >
                  and ${criterion.condition}
                  <foreach collection="criterion.value" item="listItem" open="(" close=")" separator="," >
                    #{listItem}
                  </foreach>
                </when>
              </choose>
            </foreach>
          </trim>
        </if>
      </foreach>
    </where>
  </sql>
  <sql id="Base_Column_List" >
    <!--
      WARNING - @mbggenerated
      This element is automatically generated by MyBatis Generator, do not modify.
      This element was generated on Tue Jun 21 00:00:04 CST 2016.
    -->
    skey, sname, svalue, sort, remark, time_update, status, user_id, class
  </sql>
  <select id="selectByExample" resultMap="BaseResultMap" parameterType="com.qinjiangbo.gen.model.SysSetExample" >
    <!--
      WARNING - @mbggenerated
      This element is automatically generated by MyBatis Generator, do not modify.
      This element was generated on Tue Jun 21 00:00:04 CST 2016.
    -->
    select
    <if test="distinct" >
      distinct
    </if>
    'true' as QUERYID,
    <include refid="Base_Column_List" />
    from sys_set
    <if test="_parameter != null" >
      <include refid="Example_Where_Clause" />
    </if>
    <if test="orderByClause != null" >
      order by ${orderByClause}
    </if>
  </select>
  <select id="selectByPrimaryKey" resultMap="BaseResultMap" parameterType="java.lang.String" >
    <!--
      WARNING - @mbggenerated
      This element is automatically generated by MyBatis Generator, do not modify.
      This element was generated on Tue Jun 21 00:00:04 CST 2016.
    -->
    select 
    <include refid="Base_Column_List" />
    from sys_set
    where skey = #{skey,jdbcType=VARCHAR}
  </select>
  <delete id="deleteByPrimaryKey" parameterType="java.lang.String" >
    <!--
      WARNING - @mbggenerated
      This element is automatically generated by MyBatis Generator, do not modify.
      This element was generated on Tue Jun 21 00:00:04 CST 2016.
    -->
    delete from sys_set
    where skey = #{skey,jdbcType=VARCHAR}
  </delete>
  <delete id="deleteByExample" parameterType="com.qinjiangbo.gen.model.SysSetExample" >
    <!--
      WARNING - @mbggenerated
      This element is automatically generated by MyBatis Generator, do not modify.
      This element was generated on Tue Jun 21 00:00:04 CST 2016.
    -->
    delete from sys_set
    <if test="_parameter != null" >
      <include refid="Example_Where_Clause" />
    </if>
  </delete>
  <insert id="insert" parameterType="com.qinjiangbo.gen.model.SysSet" >
    <!--
      WARNING - @mbggenerated
      This element is automatically generated by MyBatis Generator, do not modify.
      This element was generated on Tue Jun 21 00:00:04 CST 2016.
    -->
    insert into sys_set (skey, sname, svalue, 
      sort, remark, time_update, 
      status, user_id, class
      )
    values (#{skey,jdbcType=VARCHAR}, #{sname,jdbcType=VARCHAR}, #{svalue,jdbcType=VARCHAR}, 
      #{sort,jdbcType=INTEGER}, #{remark,jdbcType=VARCHAR}, #{timeUpdate,jdbcType=TIMESTAMP}, 
      #{status,jdbcType=INTEGER}, #{userId,jdbcType=BIGINT}, #{class,jdbcType=VARCHAR}
      )
  </insert>
  <insert id="insertSelective" parameterType="com.qinjiangbo.gen.model.SysSet" >
    <!--
      WARNING - @mbggenerated
      This element is automatically generated by MyBatis Generator, do not modify.
      This element was generated on Tue Jun 21 00:00:04 CST 2016.
    -->
    insert into sys_set
    <trim prefix="(" suffix=")" suffixOverrides="," >
      <if test="skey != null" >
        skey,
      </if>
      <if test="sname != null" >
        sname,
      </if>
      <if test="svalue != null" >
        svalue,
      </if>
      <if test="sort != null" >
        sort,
      </if>
      <if test="remark != null" >
        remark,
      </if>
      <if test="timeUpdate != null" >
        time_update,
      </if>
      <if test="status != null" >
        status,
      </if>
      <if test="userId != null" >
        user_id,
      </if>
      <if test="class != null" >
        class,
      </if>
    </trim>
    <trim prefix="values (" suffix=")" suffixOverrides="," >
      <if test="skey != null" >
        #{skey,jdbcType=VARCHAR},
      </if>
      <if test="sname != null" >
        #{sname,jdbcType=VARCHAR},
      </if>
      <if test="svalue != null" >
        #{svalue,jdbcType=VARCHAR},
      </if>
      <if test="sort != null" >
        #{sort,jdbcType=INTEGER},
      </if>
      <if test="remark != null" >
        #{remark,jdbcType=VARCHAR},
      </if>
      <if test="timeUpdate != null" >
        #{timeUpdate,jdbcType=TIMESTAMP},
      </if>
      <if test="status != null" >
        #{status,jdbcType=INTEGER},
      </if>
      <if test="userId != null" >
        #{userId,jdbcType=BIGINT},
      </if>
      <if test="class != null" >
        #{class,jdbcType=VARCHAR},
      </if>
    </trim>
  </insert>
  <select id="countByExample" parameterType="com.qinjiangbo.gen.model.SysSetExample" resultType="java.lang.Integer" >
    <!--
      WARNING - @mbggenerated
      This element is automatically generated by MyBatis Generator, do not modify.
      This element was generated on Tue Jun 21 00:00:04 CST 2016.
    -->
    select count(*) from sys_set
    <if test="_parameter != null" >
      <include refid="Example_Where_Clause" />
    </if>
  </select>
  <update id="updateByExampleSelective" parameterType="map" >
    <!--
      WARNING - @mbggenerated
      This element is automatically generated by MyBatis Generator, do not modify.
      This element was generated on Tue Jun 21 00:00:04 CST 2016.
    -->
    update sys_set
    <set >
      <if test="record.skey != null" >
        skey = #{record.skey,jdbcType=VARCHAR},
      </if>
      <if test="record.sname != null" >
        sname = #{record.sname,jdbcType=VARCHAR},
      </if>
      <if test="record.svalue != null" >
        svalue = #{record.svalue,jdbcType=VARCHAR},
      </if>
      <if test="record.sort != null" >
        sort = #{record.sort,jdbcType=INTEGER},
      </if>
      <if test="record.remark != null" >
        remark = #{record.remark,jdbcType=VARCHAR},
      </if>
      <if test="record.timeUpdate != null" >
        time_update = #{record.timeUpdate,jdbcType=TIMESTAMP},
      </if>
      <if test="record.status != null" >
        status = #{record.status,jdbcType=INTEGER},
      </if>
      <if test="record.userId != null" >
        user_id = #{record.userId,jdbcType=BIGINT},
      </if>
      <if test="record.class != null" >
        class = #{record.class,jdbcType=VARCHAR},
      </if>
    </set>
    <if test="_parameter != null" >
      <include refid="Update_By_Example_Where_Clause" />
    </if>
  </update>
  <update id="updateByExample" parameterType="map" >
    <!--
      WARNING - @mbggenerated
      This element is automatically generated by MyBatis Generator, do not modify.
      This element was generated on Tue Jun 21 00:00:04 CST 2016.
    -->
    update sys_set
    set skey = #{record.skey,jdbcType=VARCHAR},
      sname = #{record.sname,jdbcType=VARCHAR},
      svalue = #{record.svalue,jdbcType=VARCHAR},
      sort = #{record.sort,jdbcType=INTEGER},
      remark = #{record.remark,jdbcType=VARCHAR},
      time_update = #{record.timeUpdate,jdbcType=TIMESTAMP},
      status = #{record.status,jdbcType=INTEGER},
      user_id = #{record.userId,jdbcType=BIGINT},
      class = #{record.class,jdbcType=VARCHAR}
    <if test="_parameter != null" >
      <include refid="Update_By_Example_Where_Clause" />
    </if>
  </update>
  <update id="updateByPrimaryKeySelective" parameterType="com.qinjiangbo.gen.model.SysSet" >
    <!--
      WARNING - @mbggenerated
      This element is automatically generated by MyBatis Generator, do not modify.
      This element was generated on Tue Jun 21 00:00:04 CST 2016.
    -->
    update sys_set
    <set >
      <if test="sname != null" >
        sname = #{sname,jdbcType=VARCHAR},
      </if>
      <if test="svalue != null" >
        svalue = #{svalue,jdbcType=VARCHAR},
      </if>
      <if test="sort != null" >
        sort = #{sort,jdbcType=INTEGER},
      </if>
      <if test="remark != null" >
        remark = #{remark,jdbcType=VARCHAR},
      </if>
      <if test="timeUpdate != null" >
        time_update = #{timeUpdate,jdbcType=TIMESTAMP},
      </if>
      <if test="status != null" >
        status = #{status,jdbcType=INTEGER},
      </if>
      <if test="userId != null" >
        user_id = #{userId,jdbcType=BIGINT},
      </if>
      <if test="class != null" >
        class = #{class,jdbcType=VARCHAR},
      </if>
    </set>
    where skey = #{skey,jdbcType=VARCHAR}
  </update>
  <update id="updateByPrimaryKey" parameterType="com.qinjiangbo.gen.model.SysSet" >
    <!--
      WARNING - @mbggenerated
      This element is automatically generated by MyBatis Generator, do not modify.
      This element was generated on Tue Jun 21 00:00:04 CST 2016.
    -->
    update sys_set
    set sname = #{sname,jdbcType=VARCHAR},
      svalue = #{svalue,jdbcType=VARCHAR},
      sort = #{sort,jdbcType=INTEGER},
      remark = #{remark,jdbcType=VARCHAR},
      time_update = #{timeUpdate,jdbcType=TIMESTAMP},
      status = #{status,jdbcType=INTEGER},
      user_id = #{userId,jdbcType=BIGINT},
      class = #{class,jdbcType=VARCHAR}
    where skey = #{skey,jdbcType=VARCHAR}
  </update>
</mapper>