<?xml version="1.0" encoding="UTF-8" ?>
<!DOCTYPE mapper PUBLIC "-//mybatis.org//DTD Mapper 3.0//EN" "http://mybatis.org/dtd/mybatis-3-mapper.dtd" >
<mapper namespace="com.qinjiangbo.gen.dao.WdWorkCheckMapper" >
  <resultMap id="BaseResultMap" type="com.qinjiangbo.gen.model.WdWorkCheck" >
    <!--
      WARNING - @mbggenerated
      This element is automatically generated by MyBatis Generator, do not modify.
      This element was generated on Tue Jun 21 00:00:04 CST 2016.
    -->
    <id column="check_id" property="checkId" jdbcType="BIGINT" />
    <result column="wk_id" property="wkId" jdbcType="BIGINT" />
    <result column="wid" property="wid" jdbcType="BIGINT" />
    <result column="num_sec" property="numSec" jdbcType="BIGINT" />
    <result column="is_right" property="isRight" jdbcType="BIGINT" />
    <result column="wid_ans" property="widAns" jdbcType="BIGINT" />
    <result column="pack_id" property="packId" jdbcType="BIGINT" />
    <result column="time_update" property="timeUpdate" jdbcType="TIMESTAMP" />
  </resultMap>
  <sql id="Example_Where_Clause" >
    <!--
      WARNING - @mbggenerated
      This element is automatically generated by MyBatis Generator, do not modify.
      This element was generated on Tue Jun 21 00:00:04 CST 2016.
    -->
    <where >
      <foreach collection="oredCriteria" item="criteria" separator="or" >
        <if test="criteria.valid" >
          <trim prefix="(" suffix=")" prefixOverrides="and" >
            <foreach collection="criteria.criteria" item="criterion" >
              <choose >
                <when test="criterion.noValue" >
                  and ${criterion.condition}
                </when>
                <when test="criterion.singleValue" >
                  and ${criterion.condition} #{criterion.value}
                </when>
                <when test="criterion.betweenValue" >
                  and ${criterion.condition} #{criterion.value} and #{criterion.secondValue}
                </when>
                <when test="criterion.listValue" >
                  and ${criterion.condition}
                  <foreach collection="criterion.value" item="listItem" open="(" close=")" separator="," >
                    #{listItem}
                  </foreach>
                </when>
              </choose>
            </foreach>
          </trim>
        </if>
      </foreach>
    </where>
  </sql>
  <sql id="Update_By_Example_Where_Clause" >
    <!--
      WARNING - @mbggenerated
      This element is automatically generated by MyBatis Generator, do not modify.
      This element was generated on Tue Jun 21 00:00:04 CST 2016.
    -->
    <where >
      <foreach collection="example.oredCriteria" item="criteria" separator="or" >
        <if test="criteria.valid" >
          <trim prefix="(" suffix=")" prefixOverrides="and" >
            <foreach collection="criteria.criteria" item="criterion" >
              <choose >
                <when test="criterion.noValue" >
                  and ${criterion.condition}
                </when>
                <when test="criterion.singleValue" >
                  and ${criterion.condition} #{criterion.value}
                </when>
                <when test="criterion.betweenValue" >
                  and ${criterion.condition} #{criterion.value} and #{criterion.secondValue}
                </when>
                <when test="criterion.listValue" >
                  and ${criterion.condition}
                  <foreach collection="criterion.value" item="listItem" open="(" close=")" separator="," >
                    #{listItem}
                  </foreach>
                </when>
              </choose>
            </foreach>
          </trim>
        </if>
      </foreach>
    </where>
  </sql>
  <sql id="Base_Column_List" >
    <!--
      WARNING - @mbggenerated
      This element is automatically generated by MyBatis Generator, do not modify.
      This element was generated on Tue Jun 21 00:00:04 CST 2016.
    -->
    check_id, wk_id, wid, num_sec, is_right, wid_ans, pack_id, time_update
  </sql>
  <select id="selectByExample" resultMap="BaseResultMap" parameterType="com.qinjiangbo.gen.model.WdWorkCheckExample" >
    <!--
      WARNING - @mbggenerated
      This element is automatically generated by MyBatis Generator, do not modify.
      This element was generated on Tue Jun 21 00:00:04 CST 2016.
    -->
    select
    <if test="distinct" >
      distinct
    </if>
    'true' as QUERYID,
    <include refid="Base_Column_List" />
    from wd_work_check
    <if test="_parameter != null" >
      <include refid="Example_Where_Clause" />
    </if>
    <if test="orderByClause != null" >
      order by ${orderByClause}
    </if>
  </select>
  <select id="selectByPrimaryKey" resultMap="BaseResultMap" parameterType="java.lang.Long" >
    <!--
      WARNING - @mbggenerated
      This element is automatically generated by MyBatis Generator, do not modify.
      This element was generated on Tue Jun 21 00:00:04 CST 2016.
    -->
    select 
    <include refid="Base_Column_List" />
    from wd_work_check
    where check_id = #{checkId,jdbcType=BIGINT}
  </select>
  <delete id="deleteByPrimaryKey" parameterType="java.lang.Long" >
    <!--
      WARNING - @mbggenerated
      This element is automatically generated by MyBatis Generator, do not modify.
      This element was generated on Tue Jun 21 00:00:04 CST 2016.
    -->
    delete from wd_work_check
    where check_id = #{checkId,jdbcType=BIGINT}
  </delete>
  <delete id="deleteByExample" parameterType="com.qinjiangbo.gen.model.WdWorkCheckExample" >
    <!--
      WARNING - @mbggenerated
      This element is automatically generated by MyBatis Generator, do not modify.
      This element was generated on Tue Jun 21 00:00:04 CST 2016.
    -->
    delete from wd_work_check
    <if test="_parameter != null" >
      <include refid="Example_Where_Clause" />
    </if>
  </delete>
  <insert id="insert" parameterType="com.qinjiangbo.gen.model.WdWorkCheck" >
    <!--
      WARNING - @mbggenerated
      This element is automatically generated by MyBatis Generator, do not modify.
      This element was generated on Tue Jun 21 00:00:04 CST 2016.
    -->
    insert into wd_work_check (check_id, wk_id, wid, 
      num_sec, is_right, wid_ans, 
      pack_id, time_update)
    values (#{checkId,jdbcType=BIGINT}, #{wkId,jdbcType=BIGINT}, #{wid,jdbcType=BIGINT}, 
      #{numSec,jdbcType=BIGINT}, #{isRight,jdbcType=BIGINT}, #{widAns,jdbcType=BIGINT}, 
      #{packId,jdbcType=BIGINT}, #{timeUpdate,jdbcType=TIMESTAMP})
  </insert>
  <insert id="insertSelective" parameterType="com.qinjiangbo.gen.model.WdWorkCheck" >
    <!--
      WARNING - @mbggenerated
      This element is automatically generated by MyBatis Generator, do not modify.
      This element was generated on Tue Jun 21 00:00:04 CST 2016.
    -->
    insert into wd_work_check
    <trim prefix="(" suffix=")" suffixOverrides="," >
      <if test="checkId != null" >
        check_id,
      </if>
      <if test="wkId != null" >
        wk_id,
      </if>
      <if test="wid != null" >
        wid,
      </if>
      <if test="numSec != null" >
        num_sec,
      </if>
      <if test="isRight != null" >
        is_right,
      </if>
      <if test="widAns != null" >
        wid_ans,
      </if>
      <if test="packId != null" >
        pack_id,
      </if>
      <if test="timeUpdate != null" >
        time_update,
      </if>
    </trim>
    <trim prefix="values (" suffix=")" suffixOverrides="," >
      <if test="checkId != null" >
        #{checkId,jdbcType=BIGINT},
      </if>
      <if test="wkId != null" >
        #{wkId,jdbcType=BIGINT},
      </if>
      <if test="wid != null" >
        #{wid,jdbcType=BIGINT},
      </if>
      <if test="numSec != null" >
        #{numSec,jdbcType=BIGINT},
      </if>
      <if test="isRight != null" >
        #{isRight,jdbcType=BIGINT},
      </if>
      <if test="widAns != null" >
        #{widAns,jdbcType=BIGINT},
      </if>
      <if test="packId != null" >
        #{packId,jdbcType=BIGINT},
      </if>
      <if test="timeUpdate != null" >
        #{timeUpdate,jdbcType=TIMESTAMP},
      </if>
    </trim>
  </insert>
  <select id="countByExample" parameterType="com.qinjiangbo.gen.model.WdWorkCheckExample" resultType="java.lang.Integer" >
    <!--
      WARNING - @mbggenerated
      This element is automatically generated by MyBatis Generator, do not modify.
      This element was generated on Tue Jun 21 00:00:04 CST 2016.
    -->
    select count(*) from wd_work_check
    <if test="_parameter != null" >
      <include refid="Example_Where_Clause" />
    </if>
  </select>
  <update id="updateByExampleSelective" parameterType="map" >
    <!--
      WARNING - @mbggenerated
      This element is automatically generated by MyBatis Generator, do not modify.
      This element was generated on Tue Jun 21 00:00:04 CST 2016.
    -->
    update wd_work_check
    <set >
      <if test="record.checkId != null" >
        check_id = #{record.checkId,jdbcType=BIGINT},
      </if>
      <if test="record.wkId != null" >
        wk_id = #{record.wkId,jdbcType=BIGINT},
      </if>
      <if test="record.wid != null" >
        wid = #{record.wid,jdbcType=BIGINT},
      </if>
      <if test="record.numSec != null" >
        num_sec = #{record.numSec,jdbcType=BIGINT},
      </if>
      <if test="record.isRight != null" >
        is_right = #{record.isRight,jdbcType=BIGINT},
      </if>
      <if test="record.widAns != null" >
        wid_ans = #{record.widAns,jdbcType=BIGINT},
      </if>
      <if test="record.packId != null" >
        pack_id = #{record.packId,jdbcType=BIGINT},
      </if>
      <if test="record.timeUpdate != null" >
        time_update = #{record.timeUpdate,jdbcType=TIMESTAMP},
      </if>
    </set>
    <if test="_parameter != null" >
      <include refid="Update_By_Example_Where_Clause" />
    </if>
  </update>
  <update id="updateByExample" parameterType="map" >
    <!--
      WARNING - @mbggenerated
      This element is automatically generated by MyBatis Generator, do not modify.
      This element was generated on Tue Jun 21 00:00:04 CST 2016.
    -->
    update wd_work_check
    set check_id = #{record.checkId,jdbcType=BIGINT},
      wk_id = #{record.wkId,jdbcType=BIGINT},
      wid = #{record.wid,jdbcType=BIGINT},
      num_sec = #{record.numSec,jdbcType=BIGINT},
      is_right = #{record.isRight,jdbcType=BIGINT},
      wid_ans = #{record.widAns,jdbcType=BIGINT},
      pack_id = #{record.packId,jdbcType=BIGINT},
      time_update = #{record.timeUpdate,jdbcType=TIMESTAMP}
    <if test="_parameter != null" >
      <include refid="Update_By_Example_Where_Clause" />
    </if>
  </update>
  <update id="updateByPrimaryKeySelective" parameterType="com.qinjiangbo.gen.model.WdWorkCheck" >
    <!--
      WARNING - @mbggenerated
      This element is automatically generated by MyBatis Generator, do not modify.
      This element was generated on Tue Jun 21 00:00:04 CST 2016.
    -->
    update wd_work_check
    <set >
      <if test="wkId != null" >
        wk_id = #{wkId,jdbcType=BIGINT},
      </if>
      <if test="wid != null" >
        wid = #{wid,jdbcType=BIGINT},
      </if>
      <if test="numSec != null" >
        num_sec = #{numSec,jdbcType=BIGINT},
      </if>
      <if test="isRight != null" >
        is_right = #{isRight,jdbcType=BIGINT},
      </if>
      <if test="widAns != null" >
        wid_ans = #{widAns,jdbcType=BIGINT},
      </if>
      <if test="packId != null" >
        pack_id = #{packId,jdbcType=BIGINT},
      </if>
      <if test="timeUpdate != null" >
        time_update = #{timeUpdate,jdbcType=TIMESTAMP},
      </if>
    </set>
    where check_id = #{checkId,jdbcType=BIGINT}
  </update>
  <update id="updateByPrimaryKey" parameterType="com.qinjiangbo.gen.model.WdWorkCheck" >
    <!--
      WARNING - @mbggenerated
      This element is automatically generated by MyBatis Generator, do not modify.
      This element was generated on Tue Jun 21 00:00:04 CST 2016.
    -->
    update wd_work_check
    set wk_id = #{wkId,jdbcType=BIGINT},
      wid = #{wid,jdbcType=BIGINT},
      num_sec = #{numSec,jdbcType=BIGINT},
      is_right = #{isRight,jdbcType=BIGINT},
      wid_ans = #{widAns,jdbcType=BIGINT},
      pack_id = #{packId,jdbcType=BIGINT},
      time_update = #{timeUpdate,jdbcType=TIMESTAMP}
    where check_id = #{checkId,jdbcType=BIGINT}
  </update>
</mapper>